{
  "CF123291888": {
    "contest_id": 1553,
    "language": "Java 11",
    "path": "codeforces\\1553\\A.java",
    "platform": "Codeforces",
    "problem_index": "A",
    "problem_name": "Digits Sum",
    "problem_url": "https://codeforces.com/contest/1553/problem/A",
    "submission_id": "CF123291888",
    "submission_url": "https://codeforces.com/contest/1553/submission/123291888",
    "tags": [
      "math",
      "number theory",
      "*800"
    ],
    "timestamp": "Jul/22/2021 20:10"
  },
  "CF123305055": {
    "contest_id": 1553,
    "language": "Java 8",
    "path": "codeforces\\1553\\B.java",
    "platform": "Codeforces",
    "problem_index": "B",
    "problem_name": "Reverse String",
    "problem_url": "https://codeforces.com/contest/1553/problem/B",
    "submission_id": "CF123305055",
    "submission_url": "https://codeforces.com/contest/1553/submission/123305055",
    "tags": [
      "brute force",
      "dp",
      "hashing",
      "implementation",
      "strings",
      "*1300"
    ],
    "timestamp": "Jul/22/2021 20:31"
  },
  "CF123322122": {
    "contest_id": 1553,
    "language": "Java 8",
    "path": "codeforces\\1553\\C.java",
    "platform": "Codeforces",
    "problem_index": "C",
    "problem_name": "Penalty",
    "problem_url": "https://codeforces.com/contest/1553/problem/C",
    "submission_id": "CF123322122",
    "submission_url": "https://codeforces.com/contest/1553/submission/123322122",
    "tags": [
      "bitmasks",
      "brute force",
      "dp",
      "greedy",
      "*1200"
    ],
    "timestamp": "Jul/22/2021 21:07"
  },
  "CF123334488": {
    "contest_id": 1553,
    "language": "Java 8",
    "path": "codeforces\\1553\\D.java",
    "platform": "Codeforces",
    "problem_index": "D",
    "problem_name": "Backspace",
    "problem_url": "https://codeforces.com/contest/1553/problem/D",
    "submission_id": "CF123334488",
    "submission_url": "https://codeforces.com/contest/1553/submission/123334488",
    "tags": [
      "dp",
      "greedy",
      "strings",
      "two pointers",
      "*1500"
    ],
    "timestamp": "Jul/22/2021 21:40"
  },
  "CF123363294": {
    "contest_id": 1550,
    "language": "Java 8",
    "path": "codeforces\\1550\\A.java",
    "platform": "Codeforces",
    "problem_index": "A",
    "problem_name": "Find The Array",
    "problem_url": "https://codeforces.com/contest/1550/problem/A",
    "submission_id": "CF123363294",
    "submission_url": "https://codeforces.com/contest/1550/submission/123363294",
    "tags": [
      "greedy",
      "math",
      "*800"
    ],
    "timestamp": "Jul/23/2021 01:19"
  },
  "CF123363319": {
    "contest_id": 1550,
    "language": "Java 8",
    "path": "codeforces\\1550\\B.java",
    "platform": "Codeforces",
    "problem_index": "B",
    "problem_name": "Maximum Cost Deletion",
    "problem_url": "https://codeforces.com/contest/1550/problem/B",
    "submission_id": "CF123363319",
    "submission_url": "https://codeforces.com/contest/1550/submission/123363319",
    "tags": [
      "greedy",
      "math",
      "*1000"
    ],
    "timestamp": "Jul/23/2021 01:20"
  },
  "CF123363366": {
    "contest_id": 1546,
    "language": "Java 8",
    "path": "codeforces\\1546\\A.java",
    "platform": "Codeforces",
    "problem_index": "A",
    "problem_name": "AquaMoon and Two Arrays",
    "problem_url": "https://codeforces.com/contest/1546/problem/A",
    "submission_id": "CF123363366",
    "submission_url": "https://codeforces.com/contest/1546/submission/123363366",
    "tags": [
      "brute force",
      "greedy",
      "*800"
    ],
    "timestamp": "Jul/23/2021 01:20"
  },
  "CF123363419": {
    "contest_id": 1547,
    "language": "Java 8",
    "path": "codeforces\\1547\\A.java",
    "platform": "Codeforces",
    "problem_index": "A",
    "problem_name": "Shortest Path with Obstacle",
    "problem_url": "https://codeforces.com/contest/1547/problem/A",
    "submission_id": "CF123363419",
    "submission_url": "https://codeforces.com/contest/1547/submission/123363419",
    "tags": [
      "implementation",
      "math",
      "*800"
    ],
    "timestamp": "Jul/23/2021 01:21"
  },
  "CF123363433": {
    "contest_id": 1547,
    "language": "Java 8",
    "path": "codeforces\\1547\\B.java",
    "platform": "Codeforces",
    "problem_index": "B",
    "problem_name": "Alphabetical Strings",
    "problem_url": "https://codeforces.com/contest/1547/problem/B",
    "submission_id": "CF123363433",
    "submission_url": "https://codeforces.com/contest/1547/submission/123363433",
    "tags": [
      "greedy",
      "implementation",
      "strings",
      "*800"
    ],
    "timestamp": "Jul/23/2021 01:22"
  },
  "CF124063655": {
    "contest_id": 1551,
    "language": "Java 8",
    "path": "codeforces\\1551\\E.java",
    "platform": "Codeforces",
    "problem_index": "E",
    "problem_name": "Fixed Points",
    "problem_url": "https://codeforces.com/contest/1551/problem/E",
    "submission_id": "CF124063655",
    "submission_url": "https://codeforces.com/contest/1551/submission/124063655",
    "tags": [
      "binary search",
      "brute force",
      "dp",
      "*2000"
    ],
    "timestamp": "Jul/29/2021 01:17"
  },
  "CF124063781": {
    "contest_id": 1551,
    "language": "Java 8",
    "path": "codeforces\\1551\\E.java",
    "platform": "Codeforces",
    "problem_index": "E",
    "problem_name": "Fixed Points",
    "problem_url": "https://codeforces.com/contest/1551/problem/E",
    "submission_id": "CF124063781",
    "submission_url": "https://codeforces.com/contest/1551/submission/124063781",
    "tags": [
      "binary search",
      "brute force",
      "dp",
      "*2000"
    ],
    "timestamp": "Jul/29/2021 01:20"
  },
  "CF124063796": {
    "contest_id": 1551,
    "language": "Java 8",
    "path": "codeforces\\1551\\E.java",
    "platform": "Codeforces",
    "problem_index": "E",
    "problem_name": "Fixed Points",
    "problem_url": "https://codeforces.com/contest/1551/problem/E",
    "submission_id": "CF124063796",
    "submission_url": "https://codeforces.com/contest/1551/submission/124063796",
    "tags": [
      "binary search",
      "brute force",
      "dp",
      "*2000"
    ],
    "timestamp": "Jul/29/2021 01:20"
  },
  "CF124063822": {
    "contest_id": 1551,
    "language": "Java 8",
    "path": "codeforces\\1551\\E.java",
    "platform": "Codeforces",
    "problem_index": "E",
    "problem_name": "Fixed Points",
    "problem_url": "https://codeforces.com/contest/1551/problem/E",
    "submission_id": "CF124063822",
    "submission_url": "https://codeforces.com/contest/1551/submission/124063822",
    "tags": [
      "binary search",
      "brute force",
      "dp",
      "*2000"
    ],
    "timestamp": "Jul/29/2021 01:21"
  },
  "CF124143769": {
    "contest_id": 1554,
    "language": "Java 8",
    "path": "codeforces\\1554\\A.java",
    "platform": "Codeforces",
    "problem_index": "A",
    "problem_name": "Cherry",
    "problem_url": "https://codeforces.com/contest/1554/problem/A",
    "submission_id": "CF124143769",
    "submission_url": "https://codeforces.com/contest/1554/submission/124143769",
    "tags": [
      "greedy",
      "*800"
    ],
    "timestamp": "Jul/29/2021 20:30"
  },
  "CF124193263": {
    "contest_id": 1554,
    "language": "Java 8",
    "path": "codeforces\\1554\\B.java",
    "platform": "Codeforces",
    "problem_index": "B",
    "problem_name": "Cobb",
    "problem_url": "https://codeforces.com/contest/1554/problem/B",
    "submission_id": "CF124193263",
    "submission_url": "https://codeforces.com/contest/1554/submission/124193263",
    "tags": [
      "bitmasks",
      "brute force",
      "greedy",
      "math",
      "*1700"
    ],
    "timestamp": "Jul/29/2021 23:55"
  },
  "CF124193399": {
    "contest_id": 1554,
    "language": "Java 8",
    "path": "codeforces\\1554\\B.java",
    "platform": "Codeforces",
    "problem_index": "B",
    "problem_name": "Cobb",
    "problem_url": "https://codeforces.com/contest/1554/problem/B",
    "submission_id": "CF124193399",
    "submission_url": "https://codeforces.com/contest/1554/submission/124193399",
    "tags": [
      "bitmasks",
      "brute force",
      "greedy",
      "math",
      "*1700"
    ],
    "timestamp": "Jul/29/2021 23:57"
  },
  "CF124193590": {
    "contest_id": 1554,
    "language": "Java 8",
    "path": "codeforces\\1554\\B.java",
    "platform": "Codeforces",
    "problem_index": "B",
    "problem_name": "Cobb",
    "problem_url": "https://codeforces.com/contest/1554/problem/B",
    "submission_id": "CF124193590",
    "submission_url": "https://codeforces.com/contest/1554/submission/124193590",
    "tags": [
      "bitmasks",
      "brute force",
      "greedy",
      "math",
      "*1700"
    ],
    "timestamp": "Jul/29/2021 23:58"
  },
  "CF124198346": {
    "contest_id": 1554,
    "language": "Java 8",
    "path": "codeforces\\1554\\C.java",
    "platform": "Codeforces",
    "problem_index": "C",
    "problem_name": "Mikasa",
    "problem_url": "https://codeforces.com/contest/1554/problem/C",
    "submission_id": "CF124198346",
    "submission_url": "https://codeforces.com/contest/1554/submission/124198346",
    "tags": [
      "binary search",
      "bitmasks",
      "greedy",
      "implementation",
      "*1800"
    ],
    "timestamp": "Jul/30/2021 00:54"
  },
  "CF124200017": {
    "contest_id": 1554,
    "language": "Java 11",
    "path": "codeforces\\1554\\D.java",
    "platform": "Codeforces",
    "problem_index": "D",
    "problem_name": "Diane",
    "problem_url": "https://codeforces.com/contest/1554/problem/D",
    "submission_id": "CF124200017",
    "submission_url": "https://codeforces.com/contest/1554/submission/124200017",
    "tags": [
      "constructive algorithms",
      "greedy",
      "strings",
      "*1800"
    ],
    "timestamp": "Jul/30/2021 01:17"
  },
  "CF124200532": {
    "contest_id": 1554,
    "language": "Java 11",
    "path": "codeforces\\1554\\D.java",
    "platform": "Codeforces",
    "problem_index": "D",
    "problem_name": "Diane",
    "problem_url": "https://codeforces.com/contest/1554/problem/D",
    "submission_id": "CF124200532",
    "submission_url": "https://codeforces.com/contest/1554/submission/124200532",
    "tags": [
      "constructive algorithms",
      "greedy",
      "strings",
      "*1800"
    ],
    "timestamp": "Jul/30/2021 01:25"
  },
  "CF124202884": {
    "contest_id": 1554,
    "language": "Java 11",
    "path": "codeforces\\1554\\C.java",
    "platform": "Codeforces",
    "problem_index": "C",
    "problem_name": "Mikasa",
    "problem_url": "https://codeforces.com/contest/1554/problem/C",
    "submission_id": "CF124202884",
    "submission_url": "https://codeforces.com/contest/1554/submission/124202884",
    "tags": [
      "binary search",
      "bitmasks",
      "greedy",
      "implementation",
      "*1800"
    ],
    "timestamp": "Jul/30/2021 02:07"
  },
  "CF124283728": {
    "contest_id": 1555,
    "language": "Java 8",
    "path": "codeforces\\1555\\A.java",
    "platform": "Codeforces",
    "problem_index": "A",
    "problem_name": "PizzaForces",
    "problem_url": "https://codeforces.com/contest/1555/problem/A",
    "submission_id": "CF124283728",
    "submission_url": "https://codeforces.com/contest/1555/submission/124283728",
    "tags": [
      "brute force",
      "math",
      "*900"
    ],
    "timestamp": "Jul/30/2021 20:15"
  },
  "CF124316682": {
    "contest_id": 1555,
    "language": "Java 8",
    "path": "codeforces\\1555\\C.java",
    "platform": "Codeforces",
    "problem_index": "C",
    "problem_name": "Coin Rows",
    "problem_url": "https://codeforces.com/contest/1555/problem/C",
    "submission_id": "CF124316682",
    "submission_url": "https://codeforces.com/contest/1555/submission/124316682",
    "tags": [
      "brute force",
      "constructive algorithms",
      "dp",
      "implementation",
      "*1300"
    ],
    "timestamp": "Jul/30/2021 21:06"
  },
  "CF124317048": {
    "contest_id": 1555,
    "language": "Java 8",
    "path": "codeforces\\1555\\C.java",
    "platform": "Codeforces",
    "problem_index": "C",
    "problem_name": "Coin Rows",
    "problem_url": "https://codeforces.com/contest/1555/problem/C",
    "submission_id": "CF124317048",
    "submission_url": "https://codeforces.com/contest/1555/submission/124317048",
    "tags": [
      "brute force",
      "constructive algorithms",
      "dp",
      "implementation",
      "*1300"
    ],
    "timestamp": "Jul/30/2021 21:07"
  },
  "CF124324006": {
    "contest_id": 1555,
    "language": "Java 8",
    "path": "codeforces\\1555\\B.java",
    "platform": "Codeforces",
    "problem_index": "B",
    "problem_name": "Two Tables",
    "problem_url": "https://codeforces.com/contest/1555/problem/B",
    "submission_id": "CF124324006",
    "submission_url": "https://codeforces.com/contest/1555/submission/124324006",
    "tags": [
      "brute force",
      "*1300"
    ],
    "timestamp": "Jul/30/2021 21:22"
  },
  "CF124340784": {
    "contest_id": 1555,
    "language": "Java 11",
    "path": "codeforces\\1555\\D.java",
    "platform": "Codeforces",
    "problem_index": "D",
    "problem_name": "Say No to Palindromes",
    "problem_url": "https://codeforces.com/contest/1555/problem/D",
    "submission_id": "CF124340784",
    "submission_url": "https://codeforces.com/contest/1555/submission/124340784",
    "tags": [
      "brute force",
      "constructive algorithms",
      "dp",
      "strings",
      "*1600"
    ],
    "timestamp": "Jul/30/2021 22:01"
  },
  "CF124364991": {
    "contest_id": 1359,
    "language": "Java 8",
    "path": "codeforces\\1359\\D.java",
    "platform": "Codeforces",
    "problem_index": "D",
    "problem_name": "Yet Another Yet Another Task",
    "problem_url": "https://codeforces.com/contest/1359/problem/D",
    "submission_id": "CF124364991",
    "submission_url": "https://codeforces.com/contest/1359/submission/124364991",
    "tags": [
      "data structures",
      "dp",
      "implementation",
      "two pointers",
      "*2000"
    ],
    "timestamp": "Jul/31/2021 01:55"
  },
  "CF124499236": {
    "contest_id": 958,
    "language": "Java 8",
    "path": "codeforces\\958\\C2.java",
    "platform": "Codeforces",
    "problem_index": "C2",
    "problem_name": "Encryption (medium)",
    "problem_url": "https://codeforces.com/contest/958/problem/C2",
    "submission_id": "CF124499236",
    "submission_url": "https://codeforces.com/contest/958/submission/124499236",
    "tags": [
      "dp",
      "*2000"
    ],
    "timestamp": "Aug/01/2021 16:14"
  },
  "CF124534382": {
    "contest_id": 1549,
    "language": "Java 8",
    "path": "codeforces\\1549\\A.java",
    "platform": "Codeforces",
    "problem_index": "A",
    "problem_name": "Gregor and Cryptography",
    "problem_url": "https://codeforces.com/contest/1549/problem/A",
    "submission_id": "CF124534382",
    "submission_url": "https://codeforces.com/contest/1549/submission/124534382",
    "tags": [
      "math",
      "number theory",
      "*800"
    ],
    "timestamp": "Aug/01/2021 20:20"
  },
  "CF124551167": {
    "contest_id": 1549,
    "language": "Java 8",
    "path": "codeforces\\1549\\B.java",
    "platform": "Codeforces",
    "problem_index": "B",
    "problem_name": "Gregor and the Pawn Game",
    "problem_url": "https://codeforces.com/contest/1549/problem/B",
    "submission_id": "CF124551167",
    "submission_url": "https://codeforces.com/contest/1549/submission/124551167",
    "tags": [
      "dfs and similar",
      "dp",
      "flows",
      "graph matchings",
      "graphs",
      "greedy",
      "implementation",
      "*800"
    ],
    "timestamp": "Aug/01/2021 20:38"
  },
  "CF124707529": {
    "contest_id": 1549,
    "language": "Java 8",
    "path": "codeforces\\1549\\B.java",
    "platform": "Codeforces",
    "problem_index": "B",
    "problem_name": "Gregor and the Pawn Game",
    "problem_url": "https://codeforces.com/contest/1549/problem/B",
    "submission_id": "CF124707529",
    "submission_url": "https://codeforces.com/contest/1549/submission/124707529",
    "tags": [
      "dfs and similar",
      "dp",
      "flows",
      "graph matchings",
      "graphs",
      "greedy",
      "implementation",
      "*800"
    ],
    "timestamp": "Aug/02/2021 21:18"
  },
  "CF124708365": {
    "contest_id": 1548,
    "language": "Java 8",
    "path": "codeforces\\1548\\A.java",
    "platform": "Codeforces",
    "problem_index": "A",
    "problem_name": "Web of Lies",
    "problem_url": "https://codeforces.com/contest/1548/problem/A",
    "submission_id": "CF124708365",
    "submission_url": "https://codeforces.com/contest/1548/submission/124708365",
    "tags": [
      "brute force",
      "graphs",
      "greedy",
      "*1400"
    ],
    "timestamp": "Aug/02/2021 21:27"
  },
  "CF124708427": {
    "contest_id": 1549,
    "language": "Java 8",
    "path": "codeforces\\1549\\C.java",
    "platform": "Codeforces",
    "problem_index": "C",
    "problem_name": "Web of Lies",
    "problem_url": "https://codeforces.com/contest/1549/problem/C",
    "submission_id": "CF124708427",
    "submission_url": "https://codeforces.com/contest/1549/submission/124708427",
    "tags": [
      "graphs",
      "greedy",
      "*1400"
    ],
    "timestamp": "Aug/02/2021 21:27"
  },
  "CF124794157": {
    "contest_id": 478,
    "language": "Java 8",
    "path": "codeforces\\478\\D.java",
    "platform": "Codeforces",
    "problem_index": "D",
    "problem_name": "Red-Green Towers",
    "problem_url": "https://codeforces.com/contest/478/problem/D",
    "submission_id": "CF124794157",
    "submission_url": "https://codeforces.com/contest/478/submission/124794157",
    "tags": [
      "dp",
      "*2000"
    ],
    "timestamp": "Aug/04/2021 00:45"
  },
  "CF124794238": {
    "contest_id": 478,
    "language": "Java 8",
    "path": "codeforces\\478\\D.java",
    "platform": "Codeforces",
    "problem_index": "D",
    "problem_name": "Red-Green Towers",
    "problem_url": "https://codeforces.com/contest/478/problem/D",
    "submission_id": "CF124794238",
    "submission_url": "https://codeforces.com/contest/478/submission/124794238",
    "tags": [
      "dp",
      "*2000"
    ],
    "timestamp": "Aug/04/2021 00:47"
  },
  "CF124892704": {
    "contest_id": 1427,
    "language": "Java 8",
    "path": "codeforces\\1427\\C.java",
    "platform": "Codeforces",
    "problem_index": "C",
    "problem_name": "The Hard Work of Paparazzi",
    "problem_url": "https://codeforces.com/contest/1427/problem/C",
    "submission_id": "CF124892704",
    "submission_url": "https://codeforces.com/contest/1427/submission/124892704",
    "tags": [
      "dp",
      "*2000"
    ],
    "timestamp": "Aug/04/2021 23:57"
  },
  "CF124892746": {
    "contest_id": 1427,
    "language": "Java 8",
    "path": "codeforces\\1427\\C.java",
    "platform": "Codeforces",
    "problem_index": "C",
    "problem_name": "The Hard Work of Paparazzi",
    "problem_url": "https://codeforces.com/contest/1427/problem/C",
    "submission_id": "CF124892746",
    "submission_url": "https://codeforces.com/contest/1427/submission/124892746",
    "tags": [
      "dp",
      "*2000"
    ],
    "timestamp": "Aug/04/2021 23:57"
  },
  "CF124893420": {
    "contest_id": 1427,
    "language": "Java 11",
    "path": "codeforces\\1427\\C.java",
    "platform": "Codeforces",
    "problem_index": "C",
    "problem_name": "The Hard Work of Paparazzi",
    "problem_url": "https://codeforces.com/contest/1427/problem/C",
    "submission_id": "CF124893420",
    "submission_url": "https://codeforces.com/contest/1427/submission/124893420",
    "tags": [
      "dp",
      "*2000"
    ],
    "timestamp": "Aug/05/2021 00:06"
  },
  "CF124995552": {
    "contest_id": 1458,
    "language": "Java 8",
    "path": "codeforces\\1458\\B.java",
    "platform": "Codeforces",
    "problem_index": "B",
    "problem_name": "Glass Half Spilled",
    "problem_url": "https://codeforces.com/contest/1458/problem/B",
    "submission_id": "CF124995552",
    "submission_url": "https://codeforces.com/contest/1458/submission/124995552",
    "tags": [
      "dp",
      "*2000"
    ],
    "timestamp": "Aug/06/2021 01:32"
  },
  "CF124995617": {
    "contest_id": 1458,
    "language": "Java 11",
    "path": "codeforces\\1458\\B.java",
    "platform": "Codeforces",
    "problem_index": "B",
    "problem_name": "Glass Half Spilled",
    "problem_url": "https://codeforces.com/contest/1458/problem/B",
    "submission_id": "CF124995617",
    "submission_url": "https://codeforces.com/contest/1458/submission/124995617",
    "tags": [
      "dp",
      "*2000"
    ],
    "timestamp": "Aug/06/2021 01:33"
  },
  "CF124995624": {
    "contest_id": 1458,
    "language": "Java 8",
    "path": "codeforces\\1458\\B.java",
    "platform": "Codeforces",
    "problem_index": "B",
    "problem_name": "Glass Half Spilled",
    "problem_url": "https://codeforces.com/contest/1458/problem/B",
    "submission_id": "CF124995624",
    "submission_url": "https://codeforces.com/contest/1458/submission/124995624",
    "tags": [
      "dp",
      "*2000"
    ],
    "timestamp": "Aug/06/2021 01:33"
  },
  "CF125081828": {
    "contest_id": 1132,
    "language": "Java 8",
    "path": "codeforces\\1132\\F.java",
    "platform": "Codeforces",
    "problem_index": "F",
    "problem_name": "Clear the String",
    "problem_url": "https://codeforces.com/contest/1132/problem/F",
    "submission_id": "CF125081828",
    "submission_url": "https://codeforces.com/contest/1132/submission/125081828",
    "tags": [
      "dp",
      "*2000"
    ],
    "timestamp": "Aug/06/2021 23:54"
  },
  "CF125081920": {
    "contest_id": 1132,
    "language": "Java 8",
    "path": "codeforces\\1132\\F.java",
    "platform": "Codeforces",
    "problem_index": "F",
    "problem_name": "Clear the String",
    "problem_url": "https://codeforces.com/contest/1132/problem/F",
    "submission_id": "CF125081920",
    "submission_url": "https://codeforces.com/contest/1132/submission/125081920",
    "tags": [
      "dp",
      "*2000"
    ],
    "timestamp": "Aug/06/2021 23:55"
  },
  "CF125163821": {
    "contest_id": 1514,
    "language": "Java 8",
    "path": "codeforces\\1514\\A.java",
    "platform": "Codeforces",
    "problem_index": "A",
    "problem_name": "Perfectly Imperfect Array",
    "problem_url": "https://codeforces.com/contest/1514/problem/A",
    "submission_id": "CF125163821",
    "submission_url": "https://codeforces.com/contest/1514/submission/125163821",
    "tags": [
      "math",
      "number theory",
      "*800"
    ],
    "timestamp": "Aug/08/2021 00:01"
  },
  "CF125169096": {
    "contest_id": 201,
    "language": "Java 8",
    "path": "codeforces\\201\\C.java",
    "platform": "Codeforces",
    "problem_index": "C",
    "problem_name": "Fragile Bridges",
    "problem_url": "https://codeforces.com/contest/201/problem/C",
    "submission_id": "CF125169096",
    "submission_url": "https://codeforces.com/contest/201/submission/125169096",
    "tags": [
      "dp",
      "*2000"
    ],
    "timestamp": "Aug/08/2021 01:36"
  },
  "CF125169111": {
    "contest_id": 201,
    "language": "Java 8",
    "path": "codeforces\\201\\C.java",
    "platform": "Codeforces",
    "problem_index": "C",
    "problem_name": "Fragile Bridges",
    "problem_url": "https://codeforces.com/contest/201/problem/C",
    "submission_id": "CF125169111",
    "submission_url": "https://codeforces.com/contest/201/submission/125169111",
    "tags": [
      "dp",
      "*2000"
    ],
    "timestamp": "Aug/08/2021 01:36"
  },
  "CF125169133": {
    "contest_id": 201,
    "language": "Java 8",
    "path": "codeforces\\201\\C.java",
    "platform": "Codeforces",
    "problem_index": "C",
    "problem_name": "Fragile Bridges",
    "problem_url": "https://codeforces.com/contest/201/problem/C",
    "submission_id": "CF125169133",
    "submission_url": "https://codeforces.com/contest/201/submission/125169133",
    "tags": [
      "dp",
      "*2000"
    ],
    "timestamp": "Aug/08/2021 01:36"
  },
  "CF125408452": {
    "contest_id": 1557,
    "language": "Java 8",
    "path": "codeforces\\1557\\A.java",
    "platform": "Codeforces",
    "problem_index": "A",
    "problem_name": "Ezzat and Two Subsequences",
    "problem_url": "https://codeforces.com/contest/1557/problem/A",
    "submission_id": "CF125408452",
    "submission_url": "https://codeforces.com/contest/1557/submission/125408452",
    "tags": [
      "brute force",
      "math",
      "sortings",
      "*800"
    ],
    "timestamp": "Aug/09/2021 23:19"
  },
  "CF125408477": {
    "contest_id": 1557,
    "language": "Java 8",
    "path": "codeforces\\1557\\B.java",
    "platform": "Codeforces",
    "problem_index": "B",
    "problem_name": "Moamen and k-subarrays",
    "problem_url": "https://codeforces.com/contest/1557/problem/B",
    "submission_id": "CF125408477",
    "submission_url": "https://codeforces.com/contest/1557/submission/125408477",
    "tags": [
      "greedy",
      "sortings",
      "*1100"
    ],
    "timestamp": "Aug/09/2021 23:19"
  },
  "CF125408579": {
    "contest_id": 1557,
    "language": "Java 8",
    "path": "codeforces\\1557\\B.java",
    "platform": "Codeforces",
    "problem_index": "B",
    "problem_name": "Moamen and k-subarrays",
    "problem_url": "https://codeforces.com/contest/1557/problem/B",
    "submission_id": "CF125408579",
    "submission_url": "https://codeforces.com/contest/1557/submission/125408579",
    "tags": [
      "greedy",
      "sortings",
      "*1100"
    ],
    "timestamp": "Aug/09/2021 23:19"
  },
  "CF125408583": {
    "contest_id": 1557,
    "language": "Java 8",
    "path": "codeforces\\1557\\A.java",
    "platform": "Codeforces",
    "problem_index": "A",
    "problem_name": "Ezzat and Two Subsequences",
    "problem_url": "https://codeforces.com/contest/1557/problem/A",
    "submission_id": "CF125408583",
    "submission_url": "https://codeforces.com/contest/1557/submission/125408583",
    "tags": [
      "brute force",
      "math",
      "sortings",
      "*800"
    ],
    "timestamp": "Aug/09/2021 23:20"
  },
  "CF125512319": {
    "contest_id": 1296,
    "language": "Java 8",
    "path": "codeforces\\1296\\E2.java",
    "platform": "Codeforces",
    "problem_index": "E2",
    "problem_name": "String Coloring (hard version)",
    "problem_url": "https://codeforces.com/contest/1296/problem/E2",
    "submission_id": "CF125512319",
    "submission_url": "https://codeforces.com/contest/1296/submission/125512319",
    "tags": [
      "data structures",
      "dp",
      "*2000"
    ],
    "timestamp": "Aug/10/2021 23:43"
  },
  "CF125512579": {
    "contest_id": 1296,
    "language": "Java 8",
    "path": "codeforces\\1296\\E2.java",
    "platform": "Codeforces",
    "problem_index": "E2",
    "problem_name": "String Coloring (hard version)",
    "problem_url": "https://codeforces.com/contest/1296/problem/E2",
    "submission_id": "CF125512579",
    "submission_url": "https://codeforces.com/contest/1296/submission/125512579",
    "tags": [
      "data structures",
      "dp",
      "*2000"
    ],
    "timestamp": "Aug/10/2021 23:46"
  },
  "CF125605170": {
    "contest_id": 1288,
    "language": "Java 8",
    "path": "codeforces\\1288\\D.java",
    "platform": "Codeforces",
    "problem_index": "D",
    "problem_name": "Minimax Problem",
    "problem_url": "https://codeforces.com/contest/1288/problem/D",
    "submission_id": "CF125605170",
    "submission_url": "https://codeforces.com/contest/1288/submission/125605170",
    "tags": [
      "binary search",
      "bitmasks",
      "dp",
      "*2000"
    ],
    "timestamp": "Aug/11/2021 23:25"
  },
  "CF125698700": {
    "contest_id": 999,
    "language": "Java 8",
    "path": "codeforces\\999\\F.java",
    "platform": "Codeforces",
    "problem_index": "F",
    "problem_name": "Cards and Joy",
    "problem_url": "https://codeforces.com/contest/999/problem/F",
    "submission_id": "CF125698700",
    "submission_url": "https://codeforces.com/contest/999/submission/125698700",
    "tags": [
      "dp",
      "*2000"
    ],
    "timestamp": "Aug/12/2021 23:55"
  },
  "CF125790479": {
    "contest_id": 1207,
    "language": "Java 8",
    "path": "codeforces\\1207\\C.java",
    "platform": "Codeforces",
    "problem_index": "C",
    "problem_name": "Gas Pipeline",
    "problem_url": "https://codeforces.com/contest/1207/problem/C",
    "submission_id": "CF125790479",
    "submission_url": "https://codeforces.com/contest/1207/submission/125790479",
    "tags": [
      "dp",
      "greedy",
      "*1500"
    ],
    "timestamp": "Aug/13/2021 23:55"
  },
  "CF125790505": {
    "contest_id": 1207,
    "language": "Java 8",
    "path": "codeforces\\1207\\C.java",
    "platform": "Codeforces",
    "problem_index": "C",
    "problem_name": "Gas Pipeline",
    "problem_url": "https://codeforces.com/contest/1207/problem/C",
    "submission_id": "CF125790505",
    "submission_url": "https://codeforces.com/contest/1207/submission/125790505",
    "tags": [
      "dp",
      "greedy",
      "*1500"
    ],
    "timestamp": "Aug/13/2021 23:55"
  },
  "CF125864464": {
    "contest_id": 1509,
    "language": "Java 8",
    "path": "codeforces\\1509\\C.java",
    "platform": "Codeforces",
    "problem_index": "C",
    "problem_name": "The Sports Festival",
    "problem_url": "https://codeforces.com/contest/1509/problem/C",
    "submission_id": "CF125864464",
    "submission_url": "https://codeforces.com/contest/1509/submission/125864464",
    "tags": [
      "dp",
      "greedy",
      "*1800"
    ],
    "timestamp": "Aug/14/2021 21:48"
  },
  "CF125864509": {
    "contest_id": 1509,
    "language": "Java 8",
    "path": "codeforces\\1509\\C.java",
    "platform": "Codeforces",
    "problem_index": "C",
    "problem_name": "The Sports Festival",
    "problem_url": "https://codeforces.com/contest/1509/problem/C",
    "submission_id": "CF125864509",
    "submission_url": "https://codeforces.com/contest/1509/submission/125864509",
    "tags": [
      "dp",
      "greedy",
      "*1800"
    ],
    "timestamp": "Aug/14/2021 21:49"
  },
  "CF125871514": {
    "contest_id": 1446,
    "language": "Java 8",
    "path": "codeforces\\1446\\B.java",
    "platform": "Codeforces",
    "problem_index": "B",
    "problem_name": "Catching Cheaters",
    "problem_url": "https://codeforces.com/contest/1446/problem/B",
    "submission_id": "CF125871514",
    "submission_url": "https://codeforces.com/contest/1446/submission/125871514",
    "tags": [
      "dp",
      "strings",
      "*1800"
    ],
    "timestamp": "Aug/14/2021 23:22"
  },
  "CF125871618": {
    "contest_id": 1446,
    "language": "Java 8",
    "path": "codeforces\\1446\\B.java",
    "platform": "Codeforces",
    "problem_index": "B",
    "problem_name": "Catching Cheaters",
    "problem_url": "https://codeforces.com/contest/1446/problem/B",
    "submission_id": "CF125871618",
    "submission_url": "https://codeforces.com/contest/1446/submission/125871618",
    "tags": [
      "dp",
      "strings",
      "*1800"
    ],
    "timestamp": "Aug/14/2021 23:24"
  },
  "CF125876381": {
    "contest_id": 1381,
    "language": "Java 8",
    "path": "codeforces\\1381\\B.java",
    "platform": "Codeforces",
    "problem_index": "B",
    "problem_name": "Unmerge",
    "problem_url": "https://codeforces.com/contest/1381/problem/B",
    "submission_id": "CF125876381",
    "submission_url": "https://codeforces.com/contest/1381/submission/125876381",
    "tags": [
      "dp",
      "*1800"
    ],
    "timestamp": "Aug/15/2021 00:33"
  },
  "CF125876454": {
    "contest_id": 1381,
    "language": "Java 8",
    "path": "codeforces\\1381\\B.java",
    "platform": "Codeforces",
    "problem_index": "B",
    "problem_name": "Unmerge",
    "problem_url": "https://codeforces.com/contest/1381/problem/B",
    "submission_id": "CF125876454",
    "submission_url": "https://codeforces.com/contest/1381/submission/125876454",
    "tags": [
      "dp",
      "*1800"
    ],
    "timestamp": "Aug/15/2021 00:34"
  },
  "CF125976213": {
    "contest_id": 1559,
    "language": "Java 8",
    "path": "codeforces\\1559\\B.java",
    "platform": "Codeforces",
    "problem_index": "B",
    "problem_name": "Mocha and Red and Blue",
    "problem_url": "https://codeforces.com/contest/1559/problem/B",
    "submission_id": "CF125976213",
    "submission_url": "https://codeforces.com/contest/1559/submission/125976213",
    "tags": [
      "dp",
      "greedy",
      "*900"
    ],
    "timestamp": "Aug/15/2021 20:55"
  },
  "CF125993654": {
    "contest_id": 1559,
    "language": "Java 8",
    "path": "codeforces\\1559\\C.java",
    "platform": "Codeforces",
    "problem_index": "C",
    "problem_name": "Mocha and Hiking",
    "problem_url": "https://codeforces.com/contest/1559/problem/C",
    "submission_id": "CF125993654",
    "submission_url": "https://codeforces.com/contest/1559/submission/125993654",
    "tags": [
      "constructive algorithms",
      "graphs",
      "*1200"
    ],
    "timestamp": "Aug/15/2021 21:24"
  },
  "CF126001982": {
    "contest_id": 1559,
    "language": "Java 8",
    "path": "codeforces\\1559\\A.java",
    "platform": "Codeforces",
    "problem_index": "A",
    "problem_name": "Mocha and Math",
    "problem_url": "https://codeforces.com/contest/1559/problem/A",
    "submission_id": "CF126001982",
    "submission_url": "https://codeforces.com/contest/1559/submission/126001982",
    "tags": [
      "bitmasks",
      "constructive algorithms",
      "math",
      "*900"
    ],
    "timestamp": "Aug/15/2021 21:42"
  },
  "CF126024777": {
    "contest_id": 1559,
    "language": "Java 8",
    "path": "codeforces\\1559\\D1.java",
    "platform": "Codeforces",
    "problem_index": "D1",
    "problem_name": "Mocha and Diana (Easy Version)",
    "problem_url": "https://codeforces.com/contest/1559/problem/D1",
    "submission_id": "CF126024777",
    "submission_url": "https://codeforces.com/contest/1559/submission/126024777",
    "tags": [
      "brute force",
      "constructive algorithms",
      "dsu",
      "graphs",
      "greedy",
      "trees",
      "*1400"
    ],
    "timestamp": "Aug/16/2021 00:57"
  },
  "CF126111125": {
    "contest_id": 1437,
    "language": "Java 8",
    "path": "codeforces\\1437\\C.java",
    "platform": "Codeforces",
    "problem_index": "C",
    "problem_name": "Chef Monocarp",
    "problem_url": "https://codeforces.com/contest/1437/problem/C",
    "submission_id": "CF126111125",
    "submission_url": "https://codeforces.com/contest/1437/submission/126111125",
    "tags": [
      "dp",
      "flows",
      "graph matchings",
      "greedy",
      "math",
      "sortings",
      "*1800"
    ],
    "timestamp": "Aug/16/2021 22:13"
  },
  "CF126115849": {
    "contest_id": 1096,
    "language": "Java 8",
    "path": "codeforces\\1096\\D.java",
    "platform": "Codeforces",
    "problem_index": "D",
    "problem_name": "Easy Problem",
    "problem_url": "https://codeforces.com/contest/1096/problem/D",
    "submission_id": "CF126115849",
    "submission_url": "https://codeforces.com/contest/1096/submission/126115849",
    "tags": [
      "dp",
      "*1800"
    ],
    "timestamp": "Aug/16/2021 23:19"
  },
  "CF126115979": {
    "contest_id": 1096,
    "language": "Java 8",
    "path": "codeforces\\1096\\D.java",
    "platform": "Codeforces",
    "problem_index": "D",
    "problem_name": "Easy Problem",
    "problem_url": "https://codeforces.com/contest/1096/problem/D",
    "submission_id": "CF126115979",
    "submission_url": "https://codeforces.com/contest/1096/submission/126115979",
    "tags": [
      "dp",
      "*1800"
    ],
    "timestamp": "Aug/16/2021 23:21"
  },
  "CF126202050": {
    "contest_id": 1221,
    "language": "Java 8",
    "path": "codeforces\\1221\\D.java",
    "platform": "Codeforces",
    "problem_index": "D",
    "problem_name": "Make The Fence Great Again",
    "problem_url": "https://codeforces.com/contest/1221/problem/D",
    "submission_id": "CF126202050",
    "submission_url": "https://codeforces.com/contest/1221/submission/126202050",
    "tags": [
      "dp",
      "*1800"
    ],
    "timestamp": "Aug/17/2021 22:59"
  },
  "CF126202089": {
    "contest_id": 1221,
    "language": "Java 8",
    "path": "codeforces\\1221\\D.java",
    "platform": "Codeforces",
    "problem_index": "D",
    "problem_name": "Make The Fence Great Again",
    "problem_url": "https://codeforces.com/contest/1221/problem/D",
    "submission_id": "CF126202089",
    "submission_url": "https://codeforces.com/contest/1221/submission/126202089",
    "tags": [
      "dp",
      "*1800"
    ],
    "timestamp": "Aug/17/2021 22:59"
  },
  "CF126206274": {
    "contest_id": 997,
    "language": "Java 8",
    "path": "codeforces\\997\\B.java",
    "platform": "Codeforces",
    "problem_index": "B",
    "problem_name": "Roman Digits",
    "problem_url": "https://codeforces.com/contest/997/problem/B",
    "submission_id": "CF126206274",
    "submission_url": "https://codeforces.com/contest/997/submission/126206274",
    "tags": [
      "brute force",
      "combinatorics",
      "dp",
      "greedy",
      "math",
      "*2000"
    ],
    "timestamp": "Aug/18/2021 00:00"
  },
  "CF126206322": {
    "contest_id": 997,
    "language": "Java 8",
    "path": "codeforces\\997\\B.java",
    "platform": "Codeforces",
    "problem_index": "B",
    "problem_name": "Roman Digits",
    "problem_url": "https://codeforces.com/contest/997/problem/B",
    "submission_id": "CF126206322",
    "submission_url": "https://codeforces.com/contest/997/submission/126206322",
    "tags": [
      "brute force",
      "combinatorics",
      "dp",
      "greedy",
      "math",
      "*2000"
    ],
    "timestamp": "Aug/18/2021 00:01"
  },
  "CF126287627": {
    "contest_id": 1560,
    "language": "Java 8",
    "path": "codeforces\\1560\\A.java",
    "platform": "Codeforces",
    "problem_index": "A",
    "problem_name": "Dislike of Threes",
    "problem_url": "https://codeforces.com/contest/1560/problem/A",
    "submission_id": "CF126287627",
    "submission_url": "https://codeforces.com/contest/1560/submission/126287627",
    "tags": [
      "implementation",
      "*800"
    ],
    "timestamp": "Aug/18/2021 20:14"
  },
  "CF126323123": {
    "contest_id": 1560,
    "language": "Java 8",
    "path": "codeforces\\1560\\B.java",
    "platform": "Codeforces",
    "problem_index": "B",
    "problem_name": "Who's Opposite?",
    "problem_url": "https://codeforces.com/contest/1560/problem/B",
    "submission_id": "CF126323123",
    "submission_url": "https://codeforces.com/contest/1560/submission/126323123",
    "tags": [
      "math",
      "*800"
    ],
    "timestamp": "Aug/18/2021 20:57"
  },
  "CF126333936": {
    "contest_id": 1560,
    "language": "Java 8",
    "path": "codeforces\\1560\\C.java",
    "platform": "Codeforces",
    "problem_index": "C",
    "problem_name": "Infinity Table",
    "problem_url": "https://codeforces.com/contest/1560/problem/C",
    "submission_id": "CF126333936",
    "submission_url": "https://codeforces.com/contest/1560/submission/126333936",
    "tags": [
      "implementation",
      "math",
      "*800"
    ],
    "timestamp": "Aug/18/2021 21:15"
  },
  "CF126345805": {
    "contest_id": 1560,
    "language": "Java 8",
    "path": "codeforces\\1560\\D.java",
    "platform": "Codeforces",
    "problem_index": "D",
    "problem_name": "Make a Power of Two",
    "problem_url": "https://codeforces.com/contest/1560/problem/D",
    "submission_id": "CF126345805",
    "submission_url": "https://codeforces.com/contest/1560/submission/126345805",
    "tags": [
      "greedy",
      "math",
      "strings",
      "*1300"
    ],
    "timestamp": "Aug/18/2021 21:38"
  },
  "CF126467351": {
    "contest_id": 1012,
    "language": "Java 8",
    "path": "codeforces\\1012\\C.java",
    "platform": "Codeforces",
    "problem_index": "C",
    "problem_name": "Hills",
    "problem_url": "https://codeforces.com/contest/1012/problem/C",
    "submission_id": "CF126467351",
    "submission_url": "https://codeforces.com/contest/1012/submission/126467351",
    "tags": [
      "dp",
      "*1900"
    ],
    "timestamp": "Aug/19/2021 21:53"
  },
  "CF126467423": {
    "contest_id": 1012,
    "language": "Java 8",
    "path": "codeforces\\1012\\C.java",
    "platform": "Codeforces",
    "problem_index": "C",
    "problem_name": "Hills",
    "problem_url": "https://codeforces.com/contest/1012/problem/C",
    "submission_id": "CF126467423",
    "submission_url": "https://codeforces.com/contest/1012/submission/126467423",
    "tags": [
      "dp",
      "*1900"
    ],
    "timestamp": "Aug/19/2021 21:54"
  },
  "CF126475037": {
    "contest_id": 946,
    "language": "Java 8",
    "path": "codeforces\\946\\D.java",
    "platform": "Codeforces",
    "problem_index": "D",
    "problem_name": "Timetable",
    "problem_url": "https://codeforces.com/contest/946/problem/D",
    "submission_id": "CF126475037",
    "submission_url": "https://codeforces.com/contest/946/submission/126475037",
    "tags": [
      "dp",
      "*1800"
    ],
    "timestamp": "Aug/19/2021 23:26"
  },
  "CF126475095": {
    "contest_id": 946,
    "language": "Java 8",
    "path": "codeforces\\946\\D.java",
    "platform": "Codeforces",
    "problem_index": "D",
    "problem_name": "Timetable",
    "problem_url": "https://codeforces.com/contest/946/problem/D",
    "submission_id": "CF126475095",
    "submission_url": "https://codeforces.com/contest/946/submission/126475095",
    "tags": [
      "dp",
      "*1800"
    ],
    "timestamp": "Aug/19/2021 23:27"
  },
  "CF126555662": {
    "contest_id": 909,
    "language": "Java 8",
    "path": "codeforces\\909\\C.java",
    "platform": "Codeforces",
    "problem_index": "C",
    "problem_name": "Python Indentation",
    "problem_url": "https://codeforces.com/contest/909/problem/C",
    "submission_id": "CF126555662",
    "submission_url": "https://codeforces.com/contest/909/submission/126555662",
    "tags": [
      "dp",
      "*1800"
    ],
    "timestamp": "Aug/20/2021 21:47"
  },
  "CF126560325": {
    "contest_id": 909,
    "language": "Java 8",
    "path": "codeforces\\909\\C.java",
    "platform": "Codeforces",
    "problem_index": "C",
    "problem_name": "Python Indentation",
    "problem_url": "https://codeforces.com/contest/909/problem/C",
    "submission_id": "CF126560325",
    "submission_url": "https://codeforces.com/contest/909/submission/126560325",
    "tags": [
      "dp",
      "*1800"
    ],
    "timestamp": "Aug/20/2021 22:48"
  },
  "CF126568704": {
    "contest_id": 543,
    "language": "Java 8",
    "path": "codeforces\\543\\A.java",
    "platform": "Codeforces",
    "problem_index": "A",
    "problem_name": "Writing Code",
    "problem_url": "https://codeforces.com/contest/543/problem/A",
    "submission_id": "CF126568704",
    "submission_url": "https://codeforces.com/contest/543/submission/126568704",
    "tags": [
      "dp",
      "*1800"
    ],
    "timestamp": "Aug/21/2021 00:57"
  },
  "CF126568736": {
    "contest_id": 543,
    "language": "Java 8",
    "path": "codeforces\\543\\A.java",
    "platform": "Codeforces",
    "problem_index": "A",
    "problem_name": "Writing Code",
    "problem_url": "https://codeforces.com/contest/543/problem/A",
    "submission_id": "CF126568736",
    "submission_url": "https://codeforces.com/contest/543/submission/126568736",
    "tags": [
      "dp",
      "*1800"
    ],
    "timestamp": "Aug/21/2021 00:58"
  },
  "CF126610231": {
    "contest_id": 358,
    "language": "Java 8",
    "path": "codeforces\\358\\D.java",
    "platform": "Codeforces",
    "problem_index": "D",
    "problem_name": "Dima and Hares",
    "problem_url": "https://codeforces.com/contest/358/problem/D",
    "submission_id": "CF126610231",
    "submission_url": "https://codeforces.com/contest/358/submission/126610231",
    "tags": [
      "dp",
      "greedy",
      "*1800"
    ],
    "timestamp": "Aug/21/2021 15:35"
  },
  "CF126610275": {
    "contest_id": 358,
    "language": "Java 8",
    "path": "codeforces\\358\\D.java",
    "platform": "Codeforces",
    "problem_index": "D",
    "problem_name": "Dima and Hares",
    "problem_url": "https://codeforces.com/contest/358/problem/D",
    "submission_id": "CF126610275",
    "submission_url": "https://codeforces.com/contest/358/submission/126610275",
    "tags": [
      "dp",
      "greedy",
      "*1800"
    ],
    "timestamp": "Aug/21/2021 15:36"
  },
  "CF126610327": {
    "contest_id": 544,
    "language": "Java 8",
    "path": "codeforces\\544\\C.java",
    "platform": "Codeforces",
    "problem_index": "C",
    "problem_name": "Writing Code",
    "problem_url": "https://codeforces.com/contest/544/problem/C",
    "submission_id": "CF126610327",
    "submission_url": "https://codeforces.com/contest/544/submission/126610327",
    "tags": [
      "dp",
      "*1800"
    ],
    "timestamp": "Aug/21/2021 15:37"
  }
}